_secpy256k1.abi3.so
secpy256k1/__init__.py
secpy256k1/py.typed
secpy256k1/simple.py
secpy256k1/utils.py
secpy256k1/build_secp256k1/build.py
secpy256k1/build_secp256k1/secp256k1_headers/secp256k1.h
secpy256k1/build_secp256k1/secp256k1_headers/secp256k1_cdef.h
secpy256k1/build_secp256k1/secp256k1_headers/secp256k1_ecdh.h
secpy256k1/build_secp256k1/secp256k1_headers/secp256k1_ecdh_cdef.h
secpy256k1/build_secp256k1/secp256k1_headers/secp256k1_recovery.h
secpy256k1/examples/ex_script.py
riemann_secpy256k1-0.2.8.dist-info/LICENSE
riemann_secpy256k1-0.2.8.dist-info/METADATA
riemann_secpy256k1-0.2.8.dist-info/WHEEL
riemann_secpy256k1-0.2.8.dist-info/top_level.txt
riemann_secpy256k1-0.2.8.dist-info/RECORD
